pyc37/__init__.py
pyc37/frame.py
pyc37/pdc.py
pyc37/pmu.py
pyc37/splitter.py
pyc37/utils.py
pyc37-1.0.2.dist-info/licenses/LICENSE.txt
pyc37-1.0.2.dist-info/METADATA
pyc37-1.0.2.dist-info/WHEEL
pyc37-1.0.2.dist-info/top_level.txt
pyc37-1.0.2.dist-info/RECORD
